Metadata-Version: 1.1
Name: personal.rfoster.helloworld
Version: 5.0.0
Summary: Helloworld App to Test Alpine Images
Home-page: https://github.intuit.com/dev-patterns/docker-oicp-alpine
Author: Rod Foster
Author-email: rod_foster@intuit.com
License: GPLv3
Platform: UNKNOWN
Classifier: Development Status :: 4 - Beta
Classifier: Environment :: Console
Classifier: License :: Other/Proprietary License
Classifier: Operating System :: POSIX :: Other
Classifier: Programming Language :: Python :: 3
Classifier: Programming Language :: Python :: 3.3
Classifier: Programming Language :: Python :: 3.4
Classifier: Programming Language :: Python :: 3.5
Classifier: Programming Language :: Python :: 3.7
